Metadata-Version: 2.1
Name: pyrad-arm
Version: 0.6.0
Summary: Pyrad: Python Radar Toolkit
Home-page: https://github.com/MeteoSwiss/pyrad.git
Download-URL: https://github.com/MeteoSwiss/pyrad.git
Maintainer: MeteoSwiss Pyrad Developers
Maintainer-email: daniel.wolfensberger@meteoswiss.ch
License: BSD
Platform: Linux
